analytics_lib/__init__.py
analytics_lib/nlp_texts/__init__.py
analytics_lib/nlp_texts/for_dict_processing.py
analytics_lib/nlp_texts/psychotype.py
analytics_lib/nlp_texts/text.py
analytics_lib-0.0.2.dist-info/METADATA
analytics_lib-0.0.2.dist-info/WHEEL
analytics_lib-0.0.2.dist-info/top_level.txt
analytics_lib-0.0.2.dist-info/RECORD
