Metadata-Version: 2.1
Name: analytics-lib
Version: 0.0.2
Summary: A package for psychotyping by text
Home-page: https://github.com/lyoshamipt/bortnik_psychometry
Author: Pokhachevskiy Vsevolod
Author-email: pokhachevskiy@gmail.com
Requires-Dist: dostoevsky (==0.6.0)
Requires-Dist: morpholog (==1.6)
Requires-Dist: numpy (==1.19.5)
Requires-Dist: pandas (==1.3.5)
Requires-Dist: pingouin (==0.3.11)
Requires-Dist: pymorphy2 (==0.9.1)
Requires-Dist: pymystem3 (==0.2.0)
Requires-Dist: seaborn (==0.11.2)
Requires-Dist: simple-elmo (==0.8.0)
Requires-Dist: snowballstemmer (==2.1.0)
Requires-Dist: spacy (==3.0.6)
Requires-Dist: stanza (==1.2)
Requires-Dist: tensorflow (==2.5.0)
Requires-Dist: termcolor (==1.1.0)
Requires-Dist: wordfreq (==2.5.0)
